spmtool.py
spmtool-1.0.0.dist-info/LICENSE
spmtool-1.0.0.dist-info/METADATA
spmtool-1.0.0.dist-info/WHEEL
spmtool-1.0.0.dist-info/entry_points.txt
spmtool-1.0.0.dist-info/top_level.txt
spmtool-1.0.0.dist-info/RECORD
