Metadata-Version: 2.1
Name: spmtool
Version: 1.0.0
Summary: Read/write SPM motor controller configuration over serial connection
Author-email: Nathan Fraser <ndf-zz@6-v.org>
License: MIT
Project-URL: homepage, https://github.com/ndf-zz/spmtool
Keywords: serial,spm,kelly
Classifier: Development Status :: 3 - Alpha
Classifier: Environment :: Console
Classifier: License :: OSI Approved :: MIT License
Classifier: Operating System :: OS Independent
Classifier: Programming Language :: Python :: 3
Classifier: Topic :: Scientific/Engineering
Requires-Python: >=3.9
License-File: LICENSE
Requires-Dist: pyserial
